{
  "first name": "Stephen",
  "last name": "Clark",
  "aliases": ["gixxerblade", "Angry Pickle Guy"],
  "code": ["Javascript", "React", "Node", "HTML/CSS"],
  "askMeAbout": ["web dev", "tech", "military", "pickling"],
  "technologies": {
    "mobileApp": ["Android App"],
    "frontEnd": {
      "js": ["GatsbyJS", "React", "POjs"],
      "css": ["foundation", "sass", "bootstrap"],
      "misc": [
        "Web Accessibility",
        "UX/UI Design Principles",
        "Responsive Design"
      ]
    },
    "backEnd": {
      "js": ["node"]
    },
    "devOps": ["AWS"],
    "databases": ["Postgres", "MySql", "NoSQL", "SQL", "GraphQL"],
    "misc": ["Firebase"]
  },
  "testing": ["Jest"],
  "architecture": [
    "Serverless Architecture",
    "Progressive web applications",
    "Single page applications",
    "JAMstack"
  ],
  "misc": ["Git Source Control", "Linux"],
  "currentFocus": "e-Commerce",
  "funFact": "The first computer virus was created in 1983."
}
